data_poisoning_detector-0.1.2a1.dist-info/licenses/LICENCE.txt
poison_detector/__init__.py
poison_detector/api.py
poison_detector/detection.py
poison_detector/model.py
poison_detector/poison.py
poison_detector/preprocess.py
poison_detector/runtime.py
poison_detector/threshold.py
poison_detector/assets/multi_poison_detector_model.pt
poison_detector/assets/multi_poison_detector_thresholds.pkl
data_poisoning_detector-0.1.2a1.dist-info/METADATA
data_poisoning_detector-0.1.2a1.dist-info/WHEEL
data_poisoning_detector-0.1.2a1.dist-info/top_level.txt
data_poisoning_detector-0.1.2a1.dist-info/RECORD
