Metadata-Version: 2.4
Name: data-poisoning-detector
Version: 0.1.2a1
Summary: Data Poisoning Detection using self-supervised learning techniques
Home-page: 
Author: Lakshan Costa
Author-email: lakshancosta2@gmail.com
License: MIT
Keywords: data poisoning,self-supervised learning,machine learning,security
Classifier: Development Status :: 3 - Alpha
Classifier: Intended Audience :: Developers
Classifier: Intended Audience :: Education
Classifier: Operating System :: Microsoft :: Windows :: Windows 10
Classifier: License :: OSI Approved :: MIT License
Classifier: Programming Language :: Python :: 3.11
License-File: LICENCE.txt
Requires-Dist: numpy
Requires-Dist: pandas
Requires-Dist: scikit-learn
Requires-Dist: flask
Requires-Dist: torch
Requires-Dist: torchvision
Dynamic: author
Dynamic: author-email
Dynamic: classifier
Dynamic: description
Dynamic: description-content-type
Dynamic: keywords
Dynamic: license
Dynamic: license-file
Dynamic: requires-dist
Dynamic: summary
